i2c_protocol/write_operation.v
module write
(input clk,rst,s,rw,
input [6:0]slave_add,
input [7:0]pointer_add,
input [7:0]tx_data,
output reg busy,done,ack_error,
inout sda,
inout scl);


//parameter declaration
parameter idle=4'd0,
start=4'd1,
send_addr=4'd2,
ack_addr=4'd3,
pointer_addr=4'd5,
pointer_ack=4'd6,
send_data=4'd7,
data_ack=4'd8,
stop=4'd9;

reg[3:0]state,next_state;
reg [7:0] addr_reg;
reg [7:0]data_reg;
reg [7:0] pointer_reg;
reg[2:0] bit_count;

reg sda_out,scl_out;
assign sda=(sda_out==1'b0)?1'b0:1'bz;
assign scl=(scl_out==1'b0)?1'b0:1'bz;

wire scl_toggle;
wire scl_rise;
wire scl_fall;
assign scl_toggle = scl_en && (clk_div == 8'd49);

// scl_out = 0 before toggle means next transition is rising
assign scl_rise = scl_toggle && (scl_out == 1'b0);

// scl_out = 1 before toggle means next transition is falling
assign scl_fall = scl_toggle && (scl_out == 1'b1);

//main fsm
reg [7:0]clk_div;
reg scl_en;

//state logic
always@(posedge clk or posedge rst)begin
if(rst)begin
	state<=idle;
	
end
else begin
	state<=next_state;
end
end

//scl clk
always@(posedge clk or posedge rst)begin
	if(rst)begin
		clk_div<=0;
		scl_out<=1'b1;
	end
	else if (scl_en) begin

                if (clk_div == 8'd49) begin

                    clk_div <= 8'd0;
                    scl_out <= ~scl_out;

                end

                else begin

                    clk_div <= clk_div + 1'b1;

                end

            end

          else begin 

                clk_div <= 8'd0;
		scl_out<=1'b1;

            end
    end

//next state logic
always@(*)begin
next_state=state;
case(state)

idle:begin
if(s)
next_state=start;
end

start:begin
if(scl_fall)
next_state=send_addr;
end

send_addr:begin
if(scl_rise && bit_count==3'd0)
next_state=ack_addr;
end

ack_addr:begin
if(scl_rise)begin
if(sda==1'b0)
next_state=pointer_addr;
else
next_state=stop;
end
end

pointer_addr:begin
if(scl_rise && bit_count==3'd0)
next_state=pointer_ack;
end

pointer_ack:begin
if(scl_rise)begin
if(sda==1'b0)
next_state=send_data;
else
next_state=stop;
end
end

send_data:begin
if(scl_rise&&bit_count==3'd0)
next_state=data_ack;
end

data_ack:begin
if(scl_rise)
next_state=stop;
end

stop:begin
next_state=idle;
end

default:next_state=idle;
endcase
end



//main control
always@(posedge clk or posedge rst)begin
if(rst)begin
	sda_out<=1'b1;
	scl_en<=1'b0;
	addr_reg<=8'd0;
	pointer_reg<=8'd0;
	data_reg<=8'd0;
	bit_count<=3'd0;
	busy<=1'b0;
	done<=1'b0;
	ack_error<=1'b0;
end
else begin
done<=1'b0;
case(state)
idle: begin
	scl_en<=1'b0;
	sda_out<=1'b1;
	busy<=1'b0;
	if(s)begin
	busy<=1'b1;
        ack_error<=1'b0;
	addr_reg<={slave_add,rw};
	pointer_reg<=pointer_add;
	data_reg<=tx_data;
	bit_count<=3'd7;
	end
end

start: begin
	sda_out<=1'b0;
	scl_en<=1'b1;
	
end
	
send_addr:begin
	if(scl_fall)begin
	sda_out<=addr_reg[7];
	end
	if(bit_count!=3'd0)begin
		addr_reg<={addr_reg[6:0],1'b0};
		bit_count<=bit_count-1'b1;
		
	end
end
ack_addr:begin
	if(scl_fall) begin
		sda_out<=1'b1;
	end
	if(scl_rise)begin
       	 if (sda == 1'b0) begin
			bit_count<=3'd7;
	end
	else begin
		ack_error<=1'b1;
	end
	end
end
pointer_addr:begin
	if(scl_fall)begin
	sda_out<=pointer_reg[7];
	end
	if(bit_count!=3'd0)begin
		pointer_reg<={pointer_reg[6:0],1'b0};
		bit_count<=bit_count-1'b1;
		
	end
end

pointer_ack:begin
	if(scl_fall) begin
		sda_out<=1'b1;
	end
	if (scl_rise)begin

       	 if (sda == 1'b0) begin
			bit_count<=3'd7;
	end
	else begin
		ack_error<=1'b1;
		
	end
	end
end

send_data:begin
	if(scl_fall)begin
	sda_out<=data_reg[7];
	end
	if(bit_count!=3'd0)begin
		data_reg<={data_reg[6:0],1'b0};
		bit_count<=bit_count-1'b1;
		
	end
end		

data_ack:begin
	if(scl_fall) begin
		sda_out<=1'b1;
	end
	if (scl_rise) begin

       	 if (sda != 1'b0) begin
		ack_error<=1'b1;
	end
	end
end

stop:begin
sda_out<=1'b0;
                    if (scl_out == 1'b1) begin

                        scl_en  <= 1'b0;
                        sda_out <= 1'b1;
			busy<=1'b0;
			done<=1'b1;

                    end

                end
endcase
end
end
endmodule

i2c_protocol/write_tb.v
`timescale 1ns/1ps

module tb_write;

    //================================================
    // 1. TESTBENCH SIGNALS
    //================================================

    reg clk;
    reg rst;
    reg s;
    reg rw;

    reg [6:0] slave_add;
    reg [7:0] pointer_add;
    reg [7:0] tx_data;

    wire busy;
    wire done;
    wire ack_error;

    wire sda;
    wire scl;


    //================================================
    // 2. SLAVE ACK CONTROL
    //================================================

    reg slave_sda;

    // Slave can only pull SDA LOW.
    // When slave_sda = 1, slave releases SDA.

    assign sda = (slave_sda == 1'b0) ? 1'b0 : 1'bz;

    // Slave does not control SCL in this simple testbench
    assign scl = 1'bz;


    //================================================
    // 3. DUT INSTANTIATION
    //================================================

    write dut (

        .clk        (clk),
        .rst        (rst),
        .s          (s),
        .rw         (rw),

        .slave_add  (slave_add),
        .pointer_add(pointer_add),
        .tx_data    (tx_data),

        .busy       (busy),
        .done       (done),
        .ack_error  (ack_error),

        .sda        (sda),
        .scl        (scl)

    );


    //================================================
    // 4. CLOCK GENERATION
    //================================================

    // 10 ns clock period
    // Frequency = 100 MHz

    initial begin
        clk = 1'b0;

        forever #5 clk = ~clk;
    end


    //================================================
    // 5. I2C PULL-UP
    //================================================

    // I2C lines need pull-up resistors.

    pullup(sda);
    pullup(scl);


    //================================================
    // 6. TEST SEQUENCE
    //================================================

    initial begin

        // Initial values

        rst        = 1'b1;
        s          = 1'b0;
        rw         = 1'b0;       // 0 = WRITE

        slave_add  = 7'b1010000;
        pointer_add = 8'h39;
        tx_data     = 8'hA5;

        slave_sda  = 1'b1;       // Slave releases SDA


        // Reset
        #100;

        rst = 1'b0;


        // Wait a little
        #100;


        // Start write transaction
        s = 1'b1;


        // Keep start request active for one clock
        #10;

        s = 1'b0;


        // Wait until transaction finishes
        wait(done == 1'b1);


        #100;

        $finish;

    end


    //================================================
    // 7. SIMPLE SLAVE ACK GENERATION
    //================================================


    reg [3:0] ack_count;


    initial begin

        ack_count = 4'd0;

        forever begin

            // Wait for SCL rising edge

            @(posedge scl);


            /*
               Master releases SDA during ACK.

               If SDA is released, slave pulls it LOW.
            */

            if (dut.state == dut.ack_addr ||dut.state == dut.pointer_addr ||dut.state == dut.data_ack) begin

                slave_sda = 1'b0;

            end

            else begin

                slave_sda = 1'b1;

            end


            // Wait for SCL falling edge

            @(negedge scl);


            // Release SDA after ACK

            slave_sda = 1'b1;

        end

    end

    initial begin

        $monitor(
            "TIME=%0t | CLK=%b | SCL=%b | SDA=%b | STATE=%0d | BUSY=%b | DONE=%b | ACK_ERR=%b",
            $time,
            clk,
            scl,
            sda,
            dut.state,
            busy,
            done,
            ack_error
        );

    end


  
    initial begin

        $dumpfile("i2c_write.vcd");

        $dumpvars(0, tb_write);

    end

endmodule

i2c_protocol/i2c_write.vcd
$date
	Thu Aug 20 03:39:38 2026
$end
$version
	Icarus Verilog
$end
$timescale
	1ps
$end
$scope module tb_write $end
$var wire 1 ! scl $end
$var wire 1 " sda $end
$var wire 1 # done $end
$var wire 1 $ busy $end
$var wire 1 % ack_error $end
$var reg 4 & ack_count [3:0] $end
$var reg 1 ' clk $end
$var reg 8 ( pointer_add [7:0] $end
$var reg 1 ) rst $end
$var reg 1 * rw $end
$var reg 1 + s $end
$var reg 7 , slave_add [6:0] $end
$var reg 1 - slave_sda $end
$var reg 8 . tx_data [7:0] $end
$scope module dut $end
$var wire 1 ' clk $end
$var wire 8 / pointer_add [7:0] $end
$var wire 1 ) rst $end
$var wire 1 * rw $end
$var wire 1 + s $end
$var wire 1 ! scl $end
$var wire 1 0 scl_fall $end
$var wire 1 1 scl_rise $end
$var wire 1 2 scl_toggle $end
$var wire 1 " sda $end
$var wire 7 3 slave_add [6:0] $end
$var wire 8 4 tx_data [7:0] $end
$var parameter 4 5 ack_addr $end
$var parameter 4 6 data_ack $end
$var parameter 4 7 idle $end
$var parameter 4 8 pointer_ack $end
$var parameter 4 9 pointer_addr $end
$var parameter 4 : send_addr $end
$var parameter 4 ; send_data $end
$var parameter 4 < start $end
$var parameter 4 = stop $end
$var reg 1 % ack_error $end
$var reg 8 > addr_reg [7:0] $end
$var reg 3 ? bit_count [2:0] $end
$var reg 1 $ busy $end
$var reg 8 @ clk_div [7:0] $end
$var reg 8 A data_reg [7:0] $end
$var reg 1 # done $end
$var reg 4 B next_state [3:0] $end
$var reg 8 C pointer_reg [7:0] $end
$var reg 1 D scl_en $end
$var reg 1 E scl_out $end
$var reg 1 F sda_out $end
$var reg 4 G state [3:0] $end
$upscope $end
$upscope $end
$enddefinitions $end
$comment Show the parameter values. $end
$dumpall
b1001 =
b1 <
b111 ;
b10 :
b101 9
b110 8
b0 7
b1000 6
b11 5
$end
#0
$dumpvars
b0 G
1F
1E
0D
b0 C
b0 B
b0 A
b0 @
b0 ?
b0 >
b10100101 4
b1010000 3
02
01
00
b111001 /
b10100101 .
1-
b1010000 ,
0+
0*
1)
b111001 (
0'
b0 &
0%
0$
0#
1"
1!
$end
#5000
1'
#10000
0'
#15000
1'
#20000
0'
#25000
1'
#30000
0'
#35000
1'
#40000
0'
#45000
1'
#50000
0'
#55000
1'
#60000
0'
#65000
1'
#70000
0'
#75000
1'
#80000
0'
#85000
1'
#90000
0'
#95000
1'
#100000
0'
0)
#105000
1'
#110000
0'
#115000
1'
#120000
0'
#125000
1'
#130000
0'
#135000
1'
#140000
0'
#145000
1'
#150000
0'
#155000
1'
#160000
0'
#165000
1'
#170000
0'
#175000
1'
#180000
0'
#185000
1'
#190000
0'
#195000
1'
#200000
b1 B
0'
1+
#205000
b111 ?
b10100101 A
b111001 C
b10100000 >
1$
b1 G
1'
#210000
0'
0+
#215000
0"
1D
0F
1'
#220000
0'
#225000
b1 @
1'
#230000
0'
#235000
b10 @
1'
#240000
0'
#245000
b11 @
1'
#250000
0'
#255000
b100 @
1'
#260000
0'
#265000
b101 @
1'
#270000
0'
#275000
b110 @
1'
#280000
0'
#285000
b111 @
1'
#290000
0'
#295000
b1000 @
1'
#300000
0'
#305000
b1001 @
1'
#310000
0'
#315000
b1010 @
1'
#320000
0'
#325000
b1011 @
1'
#330000
0'
#335000
b1100 @
1'
#340000
0'
#345000
b1101 @
1'
#350000
0'
#355000
b1110 @
1'
#360000
0'
#365000
b1111 @
1'
#370000
0'
#375000
b10000 @
1'
#380000
0'
#385000
b10001 @
1'
#390000
0'
#395000
b10010 @
1'
#400000
0'
#405000
b10011 @
1'
#410000
0'
#415000
b10100 @
1'
#420000
0'
#425000
b10101 @
1'
#430000
0'
#435000
b10110 @
1'
#440000
0'
#445000
b10111 @
1'
#450000
0'
#455000
b11000 @
1'
#460000
0'
#465000
b11001 @
1'
#470000
0'
#475000
b11010 @
1'
#480000
0'
#485000
b11011 @
1'
#490000
0'
#495000
b11100 @
1'
#500000
0'
#505000
b11101 @
1'
#510000
0'
#515000
b11110 @
1'
#520000
0'
#525000
b11111 @
1'
#530000
0'
#535000
b100000 @
1'
#540000
0'
#545000
b100001 @
1'
#550000
0'
#555000
b100010 @
1'
#560000
0'
#565000
b100011 @
1'
#570000
0'
#575000
b100100 @
1'
#580000
0'
#585000
b100101 @
1'
#590000
0'
#595000
b100110 @
1'
#600000
0'
#605000
b100111 @
1'
#610000
0'
#615000
b101000 @
1'
#620000
0'
#625000
b101001 @
1'
#630000
0'
#635000
b101010 @
1'
#640000
0'
#645000
b101011 @
1'
#650000
0'
#655000
b101100 @
1'
#660000
0'
#665000
b101101 @
1'
#670000
0'
#675000
b101110 @
1'
#680000
0'
#685000
b101111 @
1'
#690000
0'
#695000
b110000 @
1'
#700000
0'
#705000
b10 B
10
12
b110001 @
1'
#710000
0'
#715000
0!
00
02
b10 G
0E
b0 @
1'
#720000
0'
#725000
b110 ?
b1000000 >
b1 @
1'
#730000
0'
#735000
b10 @
b101 ?
b10000000 >
1'
#740000
0'
#745000
b100 ?
b0 >
b11 @
1'
#750000
0'
#755000
b100 @
b11 ?
1'
#760000
0'
#765000
b10 ?
b101 @
1'
#770000
0'
#775000
b110 @
b1 ?
1'
#780000
0'
#785000
b0 ?
b111 @
1'
#790000
0'
#795000
b1000 @
1'
#800000
0'
#805000
b1001 @
1'
#810000
0'
#815000
b1010 @
1'
#820000
0'
#825000
b1011 @
1'
#830000
0'
#835000
b1100 @
1'
#840000
0'
#845000
b1101 @
1'
#850000
0'
#855000
b1110 @
1'
#860000
0'
#865000
b1111 @
1'
#870000
0'
#875000
b10000 @
1'
#880000
0'
#885000
b10001 @
1'
#890000
0'
#895000
b10010 @
1'
#900000
0'
#905000
b10011 @
1'
#910000
0'
#915000
b10100 @
1'
#920000
0'
#925000
b10101 @
1'
#930000
0'
#935000
b10110 @
1'
#940000
0'
#945000
b10111 @
1'
#950000
0'
#955000
b11000 @
1'
#960000
0'
#965000
b11001 @
1'
#970000
0'
#975000
b11010 @
1'
#980000
0'
#985000
b11011 @
1'
#990000
0'
#995000
b11100 @
1'
#1000000
0'
#1005000
b11101 @
1'
#1010000
0'
#1015000
b11110 @
1'
#1020000
0'
#1025000
b11111 @
1'
#1030000
0'
#1035000
b100000 @
1'
#1040000
0'
#1045000
b100001 @
1'
#1050000
0'
#1055000
b100010 @
1'
#1060000
0'
#1065000
b100011 @
1'
#1070000
0'
#1075000
b100100 @
1'
#1080000
0'
#1085000
b100101 @
1'
#1090000
0'
#1095000
b100110 @
1'
#1100000
0'
#1105000
b100111 @
1'
#1110000
0'
#1115000
b101000 @
1'
#1120000
0'
#1125000
b101001 @
1'
#1130000
0'
#1135000
b101010 @
1'
#1140000
0'
#1145000
b101011 @
1'
#1150000
0'
#1155000
b101100 @
1'
#1160000
0'
#1165000
b101101 @
1'
#1170000
0'
#1175000
b101110 @
1'
#1180000
0'
#1185000
b101111 @
1'
#1190000
0'
#1195000
b110000 @
1'
#1200000
0'
#1205000
b11 B
11
12
b110001 @
1'
#1210000
0'
#1215000
0-
1!
01
b11 B
02
b11 G
1E
b0 @
1'
#1220000
0'
#1225000
b1 @
1'
#1230000
0'
#1235000
b10 @
1'
#1240000
0'
#1245000
b11 @
1'
#1250000
0'
#1255000
b100 @
1'
#1260000
0'
#1265000
b101 @
1'
#1270000
0'
#1275000
b110 @
1'
#1280000
0'
#1285000
b111 @
1'
#1290000
0'
#1295000
b1000 @
1'
#1300000
0'
#1305000
b1001 @
1'
#1310000
0'
#1315000
b1010 @
1'
#1320000
0'
#1325000
b1011 @
1'
#1330000
0'
#1335000
b1100 @
1'
#1340000
0'
#1345000
b1101 @
1'
#1350000
0'
#1355000
b1110 @
1'
#1360000
0'
#1365000
b1111 @
1'
#1370000
0'
#1375000
b10000 @
1'
#1380000
0'
#1385000
b10001 @
1'
#1390000
0'
#1395000
b10010 @
1'
#1400000
0'
#1405000
b10011 @
1'
#1410000
0'
#1415000
b10100 @
1'
#1420000
0'
#1425000
b10101 @
1'
#1430000
0'
#1435000
b10110 @
1'
#1440000
0'
#1445000
b10111 @
1'
#1450000
0'
#1455000
b11000 @
1'
#1460000
0'
#1465000
b11001 @
1'
#1470000
0'
#1475000
b11010 @
1'
#1480000
0'
#1485000
b11011 @
1'
#1490000
0'
#1495000
b11100 @
1'
#1500000
0'
#1505000
b11101 @
1'
#1510000
0'
#1515000
b11110 @
1'
#1520000
0'
#1525000
b11111 @
1'
#1530000
0'
#1535000
b100000 @
1'
#1540000
0'
#1545000
b100001 @
1'
#1550000
0'
#1555000
b100010 @
1'
#1560000
0'
#1565000
b100011 @
1'
#1570000
0'
#1575000
b100100 @
1'
#1580000
0'
#1585000
b100101 @
1'
#1590000
0'
#1595000
b100110 @
1'
#1600000
0'
#1605000
b100111 @
1'
#1610000
0'
#1615000
b101000 @
1'
#1620000
0'
#1625000
b101001 @
1'
#1630000
0'
#1635000
b101010 @
1'
#1640000
0'
#1645000
b101011 @
1'
#1650000
0'
#1655000
b101100 @
1'
#1660000
0'
#1665000
b101101 @
1'
#1670000
0'
#1675000
b101110 @
1'
#1680000
0'
#1685000
b101111 @
1'
#1690000
0'
#1695000
b110000 @
1'
#1700000
0'
#1705000
10
12
b110001 @
1'
#1710000
0'
#1715000
1"
1-
0!
00
02
0E
b0 @
1F
1'
#1720000
0'
#1725000
b1 @
1'
#1730000
0'
#1735000
b10 @
1'
#1740000
0'
#1745000
b11 @
1'
#1750000
0'
#1755000
b100 @
1'
#1760000
0'
#1765000
b101 @
1'
#1770000
0'
#1775000
b110 @
1'
#1780000
0'
#1785000
b111 @
1'
#1790000
0'
#1795000
b1000 @
1'
#1800000
0'
#1805000
b1001 @
1'
#1810000
0'
#1815000
b1010 @
1'
#1820000
0'
#1825000
b1011 @
1'
#1830000
0'
#1835000
b1100 @
1'
#1840000
0'
#1845000
b1101 @
1'
#1850000
0'
#1855000
b1110 @
1'
#1860000
0'
#1865000
b1111 @
1'
#1870000
0'
#1875000
b10000 @
1'
#1880000
0'
#1885000
b10001 @
1'
#1890000
0'
#1895000
b10010 @
1'
#1900000
0'
#1905000
b10011 @
1'
#1910000
0'
#1915000
b10100 @
1'
#1920000
0'
#1925000
b10101 @
1'
#1930000
0'
#1935000
b10110 @
1'
#1940000
0'
#1945000
b10111 @
1'
#1950000
0'
#1955000
b11000 @
1'
#1960000
0'
#1965000
b11001 @
1'
#1970000
0'
#1975000
b11010 @
1'
#1980000
0'
#1985000
b11011 @
1'
#1990000
0'
#1995000
b11100 @
1'
#2000000
0'
#2005000
b11101 @
1'
#2010000
0'
#2015000
b11110 @
1'
#2020000
0'
#2025000
b11111 @
1'
#2030000
0'
#2035000
b100000 @
1'
#2040000
0'
#2045000
b100001 @
1'
#2050000
0'
#2055000
b100010 @
1'
#2060000
0'
#2065000
b100011 @
1'
#2070000
0'
#2075000
b100100 @
1'
#2080000
0'
#2085000
b100101 @
1'
#2090000
0'
#2095000
b100110 @
1'
#2100000
0'
#2105000
b100111 @
1'
#2110000
0'
#2115000
b101000 @
1'
#2120000
0'
#2125000
b101001 @
1'
#2130000
0'
#2135000
b101010 @
1'
#2140000
0'
#2145000
b101011 @
1'
#2150000
0'
#2155000
b101100 @
1'
#2160000
0'
#2165000
b101101 @
1'
#2170000
0'
#2175000
b101110 @
1'
#2180000
0'
#2185000
b101111 @
1'
#2190000
0'
#2195000
b110000 @
1'
#2200000
0'
#2205000
b1001 B
11
12
b110001 @
1'
#2210000
0'
#2215000
1!
01
b0 B
02
b1001 G
1E
b0 @
1%
1'
#2220000
0'
#2225000
1#
0$
0D
1F
b1 @
b0 G
1'
#2230000
0'
#2235000
b0 @
0#
1'
