i2c_protocol/write_shan.v
module I2C_protocol(
    input clk,
    input rst_n,
    input start,
    input [6:0] addr,
    input [7:0] data,

    inout scl,
    inout sda,

    output reg busy,
    output reg ack_error
);

    //========================================================
    // Registers
    //========================================================
    reg [3:0] state;
    reg [3:0] bit_cnt;

    reg sda_out;
    reg sda_oe;

    reg scl_out;
    reg scl_oe;

    reg [7:0] addr_reg;
    reg [7:0] data_reg;


    //========================================================
    // Open-drain SDA and SCL
    //========================================================
    assign sda = sda_oe ? sda_out : 1'bz;
    assign scl = scl_oe ? scl_out : 1'bz;


    //========================================================
    // State declarations
    //========================================================
    localparam IDLE      = 4'd0;
    localparam START     = 4'd1;

    localparam ADDR_LOW  = 4'd2;
    localparam ADDR_HIGH = 4'd3;

    localparam ACK1_LOW  = 4'd4;
    localparam ACK1_HIGH = 4'd5;

    localparam DATA_LOW  = 4'd6;
    localparam DATA_HIGH = 4'd7;

    localparam ACK2_LOW  = 4'd8;
    localparam ACK2_HIGH = 4'd9;

    localparam STOP_LOW  = 4'd10;
    localparam STOP_HIGH = 4'd11;


    //========================================================
    // FSM
    //========================================================
    always @(posedge clk or negedge rst_n)
    begin

        if (!rst_n)
        begin
            state     <= IDLE;

            bit_cnt   <= 4'd0;

            addr_reg  <= 8'd0;
            data_reg  <= 8'd0;

            sda_out   <= 1'b1;
            sda_oe    <= 1'b0;

            scl_out   <= 1'b1;
            scl_oe    <= 1'b1;

            busy      <= 1'b0;
            ack_error <= 1'b0;
        end

        else
        begin

            case (state)

                //================================================
                // IDLE
                //================================================
                IDLE:
                begin
                    scl_out <= 1'b1;
                    scl_oe  <= 1'b1;

                    sda_out <= 1'b1;
                    sda_oe  <= 1'b0;

                    busy <= 1'b0;

                    if (start)
                    begin
                        busy      <= 1'b1;

                        addr_reg  <= {addr, 1'b0};
                        data_reg  <= data;

                        bit_cnt   <= 4'd7;

                        ack_error <= 1'b0;

                        state <= START;
                    end
                end


                //================================================
                // START CONDITION
                // SDA : 1 -> 0
                // while SCL = 1
                //================================================
                START:
                begin
                    scl_out <= 1'b1;
                    scl_oe  <= 1'b1;

                    sda_out <= 1'b0;
                    sda_oe  <= 1'b1;

                    bit_cnt <= 4'd7;

                    state <= ADDR_LOW;
                end


                //================================================
                // ADDRESS LOW
                // Put address bit on SDA while SCL is LOW
                //================================================
                ADDR_LOW:
                begin
                    scl_out <= 1'b0;
                    scl_oe  <= 1'b1;

                    sda_out <= addr_reg[bit_cnt];
                    sda_oe  <= 1'b1;

                    state <= ADDR_HIGH;
                end


                //================================================
                // ADDRESS HIGH
                // Slave samples address when SCL is HIGH
                //================================================
                ADDR_HIGH:
                begin
                    scl_out <= 1'b1;
                    scl_oe  <= 1'b1;

                    if (bit_cnt == 0)
                    begin
                        state <= ACK1_LOW;
                    end

                    else
                    begin
                        bit_cnt <= bit_cnt - 1'b1;

                        state <= ADDR_LOW;
                    end
                end


                //================================================
                // ADDRESS ACK LOW
                // Release SDA so slave can ACK
                //================================================
                ACK1_LOW:
                begin
                    scl_out <= 1'b0;
                    scl_oe  <= 1'b1;

                    sda_oe <= 1'b0;

                    state <= ACK1_HIGH;
                end


                //================================================
                // ADDRESS ACK HIGH
                // Slave drives SDA = 0 for ACK
                //================================================
                ACK1_HIGH:
                begin
                    scl_out <= 1'b1;
                    scl_oe  <= 1'b1;

                    if (sda == 1'b0)
                    begin
                        bit_cnt <= 4'd7;

                        state <= DATA_LOW;
                    end

                    else
                    begin
                        ack_error <= 1'b1;

                        state <= STOP_LOW;
                    end
                end


                //================================================
                // DATA LOW
                // Put data bit on SDA while SCL is LOW
                //================================================
                DATA_LOW:
                begin
                    scl_out <= 1'b0;
                    scl_oe  <= 1'b1;

                    sda_out <= data_reg[bit_cnt];
                    sda_oe  <= 1'b1;

                    state <= DATA_HIGH;
                end


                //================================================
                // DATA HIGH
                // Slave samples data when SCL is HIGH
                //================================================
                DATA_HIGH:
                begin
                    scl_out <= 1'b1;
                    scl_oe  <= 1'b1;

                    if (bit_cnt == 0)
                    begin
                        state <= ACK2_LOW;
                    end

                    else
                    begin
                        bit_cnt <= bit_cnt - 1'b1;

                        state <= DATA_LOW;
                    end
                end


                //================================================
                // DATA ACK LOW
                // Release SDA for slave ACK
                //================================================
                ACK2_LOW:
                begin
                    scl_out <= 1'b0;
                    scl_oe  <= 1'b1;

                    sda_oe <= 1'b0;

                    state <= ACK2_HIGH;
                end


                //================================================
                // DATA ACK HIGH
                //================================================
                ACK2_HIGH:
                begin
                    scl_out <= 1'b1;
                    scl_oe  <= 1'b1;

                    if (sda == 1'b0)
                    begin
                        state <= STOP_LOW;
                    end

                    else
                    begin
                        ack_error <= 1'b1;

                        state <= STOP_LOW;
                    end
                end


                //================================================
                // STOP LOW
                // Keep SDA LOW while SCL LOW
                //================================================
                STOP_LOW:
                begin
                    scl_out <= 1'b0;
                    scl_oe  <= 1'b1;

                    sda_out <= 1'b0;
                    sda_oe  <= 1'b1;

                    state <= STOP_HIGH;
                end


                //================================================
                // STOP HIGH
                // SDA : 0 -> 1 while SCL = 1
                //================================================
                STOP_HIGH:
                begin
                    scl_out <= 1'b1;
                    scl_oe  <= 1'b1;

                    sda_out <= 1'b1;
                    sda_oe  <= 1'b0;

                    busy <= 1'b0;

                    state <= IDLE;
                end


                //================================================
                // DEFAULT
                //================================================
                default:
                begin
                    state     <= IDLE;

                    bit_cnt   <= 4'd0;

                    addr_reg  <= 8'd0;
                    data_reg  <= 8'd0;

                    sda_out   <= 1'b1;
                    sda_oe    <= 1'b0;

                    scl_out   <= 1'b1;
                    scl_oe    <= 1'b1;

                    busy      <= 1'b0;
                    ack_error <= 1'b0;
                end

            endcase
        end
    end

endmodule

i2c_protocol/write_shantb.v
`timescale 1ns / 1ps

module tb_I2C_protocol;

    reg clk;
    reg rst_n;
    reg start;

    reg [6:0] addr;
    reg [7:0] data;

    wire scl;
    wire sda;

    wire busy;
    wire ack_error;

    reg slave_ack;


    //========================================================
    // Slave pulls SDA LOW when slave_ack = 1
    //========================================================
    assign sda = slave_ack ? 1'b0 : 1'bz;


    //========================================================
    // DUT
    //========================================================
    I2C_protocol uut
    (
        .clk       (clk),
        .rst_n     (rst_n),
        .start     (start),
        .addr      (addr),
        .data      (data),
        .scl       (scl),
        .sda       (sda),
        .busy      (busy),
        .ack_error (ack_error)
    );


    //========================================================
    // 100 MHz clock
    //========================================================
    always #5 clk = ~clk;


    //========================================================
    // Test
    //========================================================
    initial
    begin

        clk       = 1'b0;
        rst_n     = 1'b0;
        start     = 1'b0;

        addr      = 7'b1010000;
        data      = 8'b10101010;

        slave_ack = 1'b0;


        //====================================================
        // RESET
        //====================================================
        #20;

        rst_n = 1'b1;


        //====================================================
        // START TRANSACTION
        //====================================================
        #20;

        start = 1'b1;

        #10;

        start = 1'b0;


        //====================================================
        // Wait until address ACK
        //====================================================
        @(posedge scl);

        // Wait until master releases SDA
        wait (uut.state == uut.ACK1_HIGH);

        slave_ack = 1'b1;

        // Keep ACK active for complete ACK clock
        @(negedge scl);

        slave_ack = 1'b0;


        //====================================================
        // Wait until DATA ACK
        //====================================================
        wait (uut.state == uut.ACK2_HIGH);

        slave_ack = 1'b1;

        @(negedge scl);

        slave_ack = 1'b0;


        //====================================================
        // Wait for STOP
        //====================================================
        wait (uut.state == uut.IDLE);

        #20;

        $finish;

    end


    //========================================================
    // VCD
    //========================================================
    initial
    begin
        $dumpfile("i2c_write.vcd");
        $dumpvars(0, tb_I2C_protocol);
    end


    //========================================================
    // Monitor
    //========================================================
    initial
    begin

        $monitor(
            "Time=%0t | START=%b | SCL=%b | SDA=%b | BUSY=%b | ACK_ERROR=%b | STATE=%0d",
            $time,
            start,
            scl,
            sda,
            busy,
            ack_error,
            uut.state
        );

    end

endmodule

i2c_protocol/i2c_write.vcd
$date
	Thu Aug 20 05:09:27 2026
$end
$version
	Icarus Verilog
$end
$timescale
	1ps
$end
$scope module tb_I2C_protocol $end
$var wire 1 ! sda $end
$var wire 1 " scl $end
$var wire 1 # busy $end
$var wire 1 $ ack_error $end
$var reg 7 % addr [6:0] $end
$var reg 1 & clk $end
$var reg 8 ' data [7:0] $end
$var reg 1 ( rst_n $end
$var reg 1 ) slave_ack $end
$var reg 1 * start $end
$scope module uut $end
$var wire 7 + addr [6:0] $end
$var wire 1 & clk $end
$var wire 8 , data [7:0] $end
$var wire 1 ( rst_n $end
$var wire 1 ! sda $end
$var wire 1 * start $end
$var wire 1 " scl $end
$var parameter 4 - ACK1_HIGH $end
$var parameter 4 . ACK1_LOW $end
$var parameter 4 / ACK2_HIGH $end
$var parameter 4 0 ACK2_LOW $end
$var parameter 4 1 ADDR_HIGH $end
$var parameter 4 2 ADDR_LOW $end
$var parameter 4 3 DATA_HIGH $end
$var parameter 4 4 DATA_LOW $end
$var parameter 4 5 IDLE $end
$var parameter 4 6 START $end
$var parameter 4 7 STOP_HIGH $end
$var parameter 4 8 STOP_LOW $end
$var reg 1 $ ack_error $end
$var reg 8 9 addr_reg [7:0] $end
$var reg 4 : bit_cnt [3:0] $end
$var reg 1 # busy $end
$var reg 8 ; data_reg [7:0] $end
$var reg 1 < scl_oe $end
$var reg 1 = scl_out $end
$var reg 1 > sda_oe $end
$var reg 1 ? sda_out $end
$var reg 4 @ state [3:0] $end
$upscope $end
$upscope $end
$enddefinitions $end
$comment Show the parameter values. $end
$dumpall
b1010 8
b1011 7
b1 6
b0 5
b110 4
b111 3
b10 2
b11 1
b1000 0
b1001 /
b100 .
b101 -
$end
#0
$dumpvars
b0 @
1?
0>
1=
1<
b0 ;
b0 :
b0 9
b10101010 ,
b1010000 +
0*
0)
0(
b10101010 '
0&
b1010000 %
0$
0#
1"
z!
$end
#5000
1&
#10000
0&
#15000
1&
#20000
0&
1(
#25000
1&
#30000
0&
#35000
1&
#40000
0&
1*
#45000
b1 @
b111 :
b10101010 ;
b10100000 9
1#
1&
#50000
0&
0*
#55000
0!
b10 @
1>
0?
1&
#60000
0&
#65000
1!
0"
b11 @
1?
0=
1&
#70000
0&
#75000
1"
b10 @
b110 :
1=
1&
#80000
0&
#85000
0!
0"
b11 @
0?
0=
1&
#90000
0&
#95000
1"
b10 @
b101 :
1=
1&
#100000
0&
#105000
1!
0"
b11 @
1?
0=
1&
#110000
0&
#115000
1"
b10 @
b100 :
1=
1&
#120000
0&
#125000
0!
0"
b11 @
0?
0=
1&
#130000
0&
#135000
1"
b10 @
b11 :
1=
1&
#140000
0&
#145000
0"
b11 @
0=
1&
#150000
0&
#155000
1"
b10 @
b10 :
1=
1&
#160000
0&
#165000
0"
b11 @
0=
1&
#170000
0&
#175000
1"
b10 @
b1 :
1=
1&
#180000
0&
#185000
0"
b11 @
0=
1&
#190000
0&
#195000
1"
b10 @
b0 :
1=
1&
#200000
0&
#205000
0"
b11 @
0=
1&
#210000
0&
#215000
1"
b100 @
1=
1&
#220000
0&
#225000
1)
0!
0"
b101 @
0>
0=
1&
#230000
0&
#235000
1"
b110 @
b111 :
1=
1&
#240000
0&
#245000
0)
1!
0"
b111 @
1>
1?
0=
1&
#250000
0&
#255000
1"
b110 @
b110 :
1=
1&
#260000
0&
#265000
0!
0"
b111 @
0?
0=
1&
#270000
0&
#275000
1"
b110 @
b101 :
1=
1&
#280000
0&
#285000
1!
0"
b111 @
1?
0=
1&
#290000
0&
#295000
1"
b110 @
b100 :
1=
1&
#300000
0&
#305000
0!
0"
b111 @
0?
0=
1&
#310000
0&
#315000
1"
b110 @
b11 :
1=
1&
#320000
0&
#325000
1!
0"
b111 @
1?
0=
1&
#330000
0&
#335000
1"
b110 @
b10 :
1=
1&
#340000
0&
#345000
0!
0"
b111 @
0?
0=
1&
#350000
0&
#355000
1"
b110 @
b1 :
1=
1&
#360000
0&
#365000
1!
0"
b111 @
1?
0=
1&
#370000
0&
#375000
1"
b110 @
b0 :
1=
1&
#380000
0&
#385000
0!
0"
b111 @
0?
0=
1&
#390000
0&
#395000
1"
b1000 @
1=
1&
#400000
0&
#405000
1)
0!
0"
b1001 @
0>
0=
1&
#410000
0&
#415000
1"
b1010 @
1=
1&
#420000
0&
#425000
0)
0"
b1011 @
1>
0=
1&
#430000
0&
#435000
z!
1"
b0 @
0#
0>
1?
1=
1&
